app.py
palettes-1.0.2.dist-info/METADATA
palettes-1.0.2.dist-info/WHEEL
palettes-1.0.2.dist-info/top_level.txt
palettes-1.0.2.dist-info/RECORD
