Metadata-Version: 2.1
Name: palettes
Version: 1.0.2
Summary: Random Hex Color Codes
Home-page: https://github.com/SafyreLyons/palettes
Author: Safyre Lyons
Author-email: lyons.safyre@gmail.com
License: The Unlicence
Platform: UNKNOWN
